ml_robust_eval/__init__.py
ml_robust_eval/crossvalidator.py
ml_robust_eval/metrics.py
ml_robust_eval/monitoring.py
ml_robust_eval/testcasegenerator.py
ml_robust_eval/vizual.py
ml_robust_eval-0.1.7.dist-info/METADATA
ml_robust_eval-0.1.7.dist-info/WHEEL
ml_robust_eval-0.1.7.dist-info/licenses/LICENSE
ml_robust_eval-0.1.7.dist-info/RECORD
