Metadata-Version: 2.4
Name: ml-robust-eval
Version: 0.1.7
Summary: ML evaluation, validation, and test case generation toolkit with production monitoring.
License: MIT
License-File: LICENSE
Keywords: machine-learning,evaluation,metrics,monitoring,prometheus,grafana
Author: vikhyat-ch
Author-email: vikhyathchoppa699@gmail.com
Requires-Python: >=3.7,<4.0
Classifier: Development Status :: 4 - Beta
Classifier: Intended Audience :: Developers
Classifier: Intended Audience :: Science/Research
Classifier: License :: OSI Approved :: MIT License
Classifier: Operating System :: OS Independent
Classifier: Programming Language :: Python :: 3
Classifier: Programming Language :: Python :: 3.7
Classifier: Programming Language :: Python :: 3.8
Classifier: Programming Language :: Python :: 3.9
Classifier: Programming Language :: Python :: 3.10
Classifier: Programming Language :: Python :: 3.11
Classifier: Programming Language :: Python :: 3.12
Classifier: Programming Language :: Python :: 3.13
Classifier: Programming Language :: Python :: 3.14
Classifier: Topic :: Scientific/Engineering :: Artificial Intelligence
Provides-Extra: monitoring
Requires-Dist: prometheus-client (>=0.18.0) ; extra == "monitoring"
